QOASecurityUtil/__init__.py
QOASecurityUtil-1.1.7.dist-info/METADATA
QOASecurityUtil-1.1.7.dist-info/WHEEL
QOASecurityUtil-1.1.7.dist-info/top_level.txt
QOASecurityUtil-1.1.7.dist-info/RECORD
