Metadata-Version: 2.1
Name: QOASecurityUtil
Version: 1.1.7
Summary: QOAToken工具
Home-page: https://github.com/leeguooooo/QOASecurity
Author: lee.guo
Author-email: leeguoo@163.com
License: BSD License
Platform: all
